<annotation>
	<folder>project dataset</folder>
	<filename>IMG_20191109_131456__02.jpg</filename>
	<path>/home/sonal/Desktop/project/datapics/project dataset/IMG_20191109_131456__02.jpg</path>
	<source>
		<database>Unknown</database>
	</source>
	<size>
		<width>3000</width>
		<height>1454</height>
		<depth>3</depth>
	</size>
	<segmented>0</segmented>
	<object>
		<name>and</name>
		<pose>Unspecified</pose>
		<truncated>0</truncated>
		<difficult>0</difficult>
		<bndbox>
			<xmin>777</xmin>
			<ymin>108</ymin>
			<xmax>1218</xmax>
			<ymax>593</ymax>
		</bndbox>
	</object>
	<object>
		<name>and</name>
		<pose>Unspecified</pose>
		<truncated>0</truncated>
		<difficult>0</difficult>
		<bndbox>
			<xmin>759</xmin>
			<ymin>812</ymin>
			<xmax>1177</xmax>
			<ymax>1278</ymax>
		</bndbox>
	</object>
	<object>
		<name>not</name>
		<pose>Unspecified</pose>
		<truncated>0</truncated>
		<difficult>0</difficult>
		<bndbox>
			<xmin>1400</xmin>
			<ymin>130</ymin>
			<xmax>1670</xmax>
			<ymax>452</ymax>
		</bndbox>
	</object>
	<object>
		<name>not</name>
		<pose>Unspecified</pose>
		<truncated>0</truncated>
		<difficult>0</difficult>
		<bndbox>
			<xmin>1344</xmin>
			<ymin>845</ymin>
			<xmax>1640</xmax>
			<ymax>1137</ymax>
		</bndbox>
	</object>
	<object>
		<name>or</name>
		<pose>Unspecified</pose>
		<truncated>0</truncated>
		<difficult>0</difficult>
		<bndbox>
			<xmin>2066</xmin>
			<ymin>393</ymin>
			<xmax>2485</xmax>
			<ymax>860</ymax>
		</bndbox>
	</object>
</annotation>
