<annotation>
	<folder>images</folder>
	<filename>IMG_20200120_174559.jpg</filename>
	<path>/home/rachita/Desktop/project/or_dataset/images/IMG_20200120_174559.jpg</path>
	<source>
		<database>Unknown</database>
	</source>
	<size>
		<width>4000</width>
		<height>3000</height>
		<depth>3</depth>
	</size>
	<segmented>0</segmented>
	<object>
		<name>or</name>
		<pose>Unspecified</pose>
		<truncated>0</truncated>
		<difficult>0</difficult>
		<bndbox>
			<xmin>722</xmin>
			<ymin>952</ymin>
			<xmax>2827</xmax>
			<ymax>2627</ymax>
		</bndbox>
	</object>
</annotation>
